frappymongoapibilling/__init__.py
frappymongoapibilling/usage_store.py
frappymongoapibilling-0.1.1.dist-info/LICENSE
frappymongoapibilling-0.1.1.dist-info/METADATA
frappymongoapibilling-0.1.1.dist-info/WHEEL
frappymongoapibilling-0.1.1.dist-info/top_level.txt
frappymongoapibilling-0.1.1.dist-info/RECORD
