Metadata-Version: 2.1
Name: frappymongoapibilling
Version: 0.1.1
Summary: MongoDB Store for the API Billing Backend
Home-page: https://github.com/ilfrich/frappy-py-api-billing-store
Author: Peter Ilfrich
Author-email: das-peter@gmx.de
License: UNKNOWN
Platform: UNKNOWN
Requires-Dist: frappyapibilling
Requires-Dist: pbumongo (>=1.0.0)
